wiliot_test_equipment/__init__.py
wiliot_test_equipment/requirements.txt
wiliot_test_equipment/version.py
wiliot_test_equipment/arduino/gpio_router/__init__.py
wiliot_test_equipment/arduino/gpio_router/gpio_router.h
wiliot_test_equipment/arduino/gpio_router/gpio_router.ino
wiliot_test_equipment/utils/__init__.py
wiliot_test_equipment/utils/get_version.py
wiliot_test_equipment/visa_test_equipment/__init__.py
wiliot_test_equipment/visa_test_equipment/gpio_router.py
wiliot_test_equipment/visa_test_equipment/smu.py
wiliot_test_equipment/visa_test_equipment/visa_test_equipment.py
wiliot_test_equipment-1.0.3.dist-info/LICENSE
wiliot_test_equipment-1.0.3.dist-info/METADATA
wiliot_test_equipment-1.0.3.dist-info/WHEEL
wiliot_test_equipment-1.0.3.dist-info/top_level.txt
wiliot_test_equipment-1.0.3.dist-info/RECORD
