Metadata-Version: 2.1
Name: wiliot_test_equipment
Version: 1.0.3
Summary: A library for interacting with external lab equipment
Home-page: 
Author: Wiliot
Author-email: support@wiliot.com
License: MIT
Project-URL: Bug Tracker, https://WILIOT-ZENDESK-URL
Classifier: Programming Language :: Python :: 3
Classifier: License :: OSI Approved :: MIT License
Classifier: Operating System :: OS Independent
Requires-Python: >=3.6
License-File: LICENSE
Requires-Dist: setuptools-scm
Requires-Dist: numpy
Requires-Dist: pyvisa
Requires-Dist: pyvisa-py
Requires-Dist: PyUSB
Requires-Dist: pyserial
